Homework_1/freq_div_2n/freq_div_2n.v
module freq_div_2n
#(
	parameter DIV     = 6                  ,
	parameter MAX_NUM = DIV / 2 - 1        ,
	parameter REG_LEN = $clog2(MAX_NUM) + 1
)
(
	input  wire clk    ,
	input  wire reset  ,

	output reg new_freq
);

reg [REG_LEN - 1:0] counter;

always @(posedge clk) begin
	if(reset)
		counter <= 0;

	else begin

		if(counter == MAX_NUM)
			counter <= 0;

		else
			counter <= counter + 1'b1;
	end
end

always @(posedge clk) begin
	if(reset)
		new_freq <= 1'b1;

	else
		if(counter == MAX_NUM)
			new_freq <= ~ new_freq;
end

endmodule

Homework_1/freq_div_2n/freq_div_2n_testbench.v
`timescale 1 ns / 100 ps

module freq_div_2n_testbench ();

reg clk = 1'b1;
always begin
	#1 clk = ~clk;
end

reg  reset;

freq_div_2n freq_div_2n (
			.clk  (clk  ),
			.reset(reset)
);

initial begin

	$dumpfile("dump.vcd"); $dumpvars();

	reset = 1'b1; #2 ; 
	reset = 1'b0; #12;

	$finish;
end

endmodule

Homework_1/freq_div_2n/dump.vcd
$date
	Thu Oct  3 20:24:56 2024
$end
$version
	Icarus Verilog
$end
$timescale
	100ps
$end
$scope module freq_div_2n_testbench $end
$var reg 1 ! clk $end
$var reg 1 " reset $end
$scope module freq_div_2n $end
$var wire 1 ! clk $end
$var wire 1 " reset $end
$var reg 1 # counter $end
$var reg 1 $ new_freq $end
$upscope $end
$upscope $end
$enddefinitions $end
#0
$dumpvars
1$
0#
1"
1!
$end
#10
0!
#20
1#
1!
0"
#30
0!
#40
0#
0$
1!
#50
0!
#60
1#
1!
#70
0!
#80
0#
1$
1!
#90
0!
#100
1#
1!
#110
0!
#120
0#
0$
1!
#130
0!
#140
1#
1!
